api/__init__.py
api/server.py
src/__init__.py
src/cli.py
src/utils.py
termai_cli-1.0.1.dist-info/METADATA
termai_cli-1.0.1.dist-info/WHEEL
termai_cli-1.0.1.dist-info/entry_points.txt
termai_cli-1.0.1.dist-info/top_level.txt
termai_cli-1.0.1.dist-info/RECORD
