Metadata-Version: 2.2
Name: termai-cli
Version: 1.0.1
Summary: AI-powered CLI for generating and executing shell commands
Home-page: https://github.com/ayushgupta4002/termai
Author: Ayush Gupta
Author-email: ayush4002gupta@gmail.com
Classifier: Programming Language :: Python :: 3
Classifier: License :: OSI Approved :: MIT License
Classifier: Operating System :: OS Independent
Classifier: Environment :: Console
Classifier: Topic :: System :: Systems Administration
Classifier: Topic :: Utilities
Requires-Python: >=3.8
Requires-Dist: typer[all]
Requires-Dist: rich
Requires-Dist: pydantic
Requires-Dist: google-generativeai
Requires-Dist: python-dotenv
Requires-Dist: langchain
Requires-Dist: langchain-google-genai
Dynamic: author
Dynamic: author-email
Dynamic: classifier
Dynamic: description
Dynamic: description-content-type
Dynamic: home-page
Dynamic: requires-dist
Dynamic: requires-python
Dynamic: summary
